{
  "url": "https://buus.amy.anykey.ch",
  "managed": "true",
  "categories": [
    "Applikationen",
    "Drucker",
    "Kundenanpassungen",
    "Self Service",
    "anykey IT"
  ],
  "computerextensionattributes": [
    "Current SSID",
    "Microsoft Office Version",
    "anyDesk ID"
  ],
  "computergroups": [
    "Clients OS X 10.13",
    "Clients OS X 10.13 greater than or equal",
    "Clients OS X 10.13 less than or equal",
    "Clients OS X 10.14",
    "Clients OS X 10.14 greater than or equal",
    "Clients OS X 10.14 less than or equal",
    "Clients OS X 10.15",
    "Clients OS X 10.15 greater than or equal",
    "Clients OS X 10.15 less than or equal",
    "Macs incompatible with macOS High Sierra",
    "Macs incompatible with macOS Mojave",
    "Microsoft Office 2016 Installed",
    "Microsoft Office 2016 Not Installed",
    "Microsoft Office 2019 Installed",
    "Microsoft Office 2019 Not Installed"
  ],
  "packages": [
    "HewlettPackardEssentials.pkg.zip",
    "HewlettPackardPrinterDrivers.pkg.zip",
    "Lernprogramme Ordner.dmg",
    "Microsoft Office 2016.pkg.zip",
    "Microsoft Office 2019.pkg.zip",
    "anykey IT Logo im jamfHelper.dmg",
    "jsssr.pkg.zip"
  ],
  "policies": [
    "Adobe Acrobat Reader DC",
    "Adobe Flash Player",
    "Assimilate Ownership",
    "Automatic Apple Software Update",
    "Enable ARD",
    "Firefox",
    "Google Chrome",
    "Google Earth Pro",
    "LehrerOffice",
    "LibreOffice",
    "OmniDiskSweeper",
    "RemoveAllMyFilesFavorite",
    "Skitch",
    "StuffIt Expander",
    "Update Inventory",
    "Update Inventory Trigger",
    "VLC Player",
    "aa anykey IT jsssr",
    "anyDesk Fernwartung",
    "anykey IT Client Bootstrap",
    "anykey IT Client Security",
    "anykey IT Client Tools",
    "anykey IT Maintenance",
    "anykey IT anytmp",
    "anykey IT jamfHelper",
    "macOS High Sierra"
  ],
  "policies_remove": [
    "Adobe Reader DC",
    "Firefox 48",
    "Google Earth",
    "Microsoft Office 2016 Serializer",
    "Microsoft Office 2019 Serializer",
    "OCCNCC2EWC",
    "OCCNCC2EWC-PLUS",
    "Oracle Java 8",
    "Oracle Java 8 Self Service",
    "TextWrangler",
    "anykey IT ASU",
    "anykey IT Browser Bootstrap",
    "anykey IT Client Logout",
    "anykey IT Client Standards",
    "anykey IT Fernwartung",
    "anykey IT Logo im jamfHelper",
    "anykeyIT Fernwartung",
    "eWolke Client"
  ],
  "mobiledeviceextensionattributes": [
    "Wartungsmodus"
  ]
}
