{
  "url": "https://sekbuelach.amy.anykey.ch",
  "managed": "true",
  "categories": [
    "Applikationen",
    "Drucker",
    "Kundenanpassungen",
    "Self Service",
    "anykey IT"
  ],
  "computerextensionattributes": [
    "Microsoft Office Version",
    "anyDesk ID"
  ],
  "computergroups": [
    "Clients OS X 10.13 greater than or equal",
    "Clients OS X 10.13 less than or equal",
    "Clients OS X 10.13",
    "Clients OS X 10.14 greater than or equal",
    "Clients OS X 10.14 less than or equal",
    "Clients OS X 10.14",
    "Microsoft Office 2016 Installed",
    "Microsoft Office 2016 Not Installed",
    "Microsoft Office 2019 Installed",
    "Microsoft Office 2019 Not Installed",
    "Macs incompatible with macOS Mojave",
    "Macs incompatible with macOS High Sierra"
  ],
  "packages": [
    "anykey IT Logo im jamfHelper.dmg",
    "jsssr.pkg.zip",
    "Microsoft Office 2016.pkg.zip",
    "Microsoft Office 2019.pkg.zip",
    "HewlettPackardPrinterDrivers.pkg.zip",
    "HewlettPackardEssentials.pkg.zip"
  ],
  "policies": [
    "Adobe AIR",
    "Adobe Acrobat Reader DC",
    "Adobe Flash Player",
    "Assimilate Ownership",
    "Audacity",
    "Carbon Copy Cloner",
    "Cyberduck",
    "Enable ARD",
    "Firefox",
    "Formular-Designer",
    "GIMP",
    "Google Chrome",
    "Google Earth Pro",
    "LehrerOffice",
    "LehrerOffice Zusatz",
    "Microsoft Office 2019",
    "Oracle Java 8",
    "RemoveAllMyFilesFavorite",
    "Skitch",
    "Skype",
    "StuffIt Expander",
    "Update Inventory",
    "Update Inventory Trigger",
    "VLC Player",
    "aa anykey IT jsssr",
    "anyDesk Fernwartung",
    "anykey IT Client Bootstrap",
    "anykey IT Client Security",
    "anykey IT Client Tools",
    "anykey IT Maintenance",
    "anykey IT anytmp",
    "anykey IT jamfHelper",
    "eWolke Web",
    "macOS High Sierra",
    "macOS Mojave"
  ],
  "policies_remove": [
    "Adobe Reader DC",
    "Google Earth",
    "Inkscape",
    "LehrerOffice Formular Designer",
    "Microsoft Office 2016 Serializer",
    "Microsoft Office 2019 Serializer",
    "OCCNCC2EWC",
    "OmniDiskSweeper",
    "Scratch 2",
    "Text Wrangler",
    "TextWrangler",
    "anykey IT ASU",
    "anykey IT Apple Software Update Sek SUS",
    "anykey IT Client Standards",
    "anykey IT Fernwartung",
    "anykeyIT Fernwartung",
    "eWolke"
  ]
}
